aiohivebot
