Metadata-Version: 2.1
Name: aiohivebot
Version: 0.2.7
Summary: Asynchonous Python client library for the HIVE blockchain
Home-page: https://github.com/pibara/aiohivebot
Author: Rob Meijer
Author-email: pibara@gmail.com
License: BSD
Keywords: hive blockchain jsonrpc
Classifier: Development Status :: 4 - Beta
Classifier: Environment :: Console
Classifier: Intended Audience :: Developers
Classifier: License :: OSI Approved :: MIT License
Classifier: Operating System :: OS Independent
Classifier: Programming Language :: Python
Classifier: Topic :: Software Development :: Libraries :: Python Modules
Requires-Python: >=3.9
License-File: LICENSE
Requires-Dist: httpx
Requires-Dist: average
Requires-Dist: dateutils
